README
setup.py
txdpce/__init__.py
txdpce/dpce.py
txdpce.egg-info/PKG-INFO
txdpce.egg-info/SOURCES.txt
txdpce.egg-info/dependency_links.txt
txdpce.egg-info/requires.txt
txdpce.egg-info/top_level.txt
txdpce/test/__init__.py
txdpce/test/test_dpce.py