Metadata-Version: 1.1
Name: txdpce
Version: 0.1.2
Summary: A Twisted class for parallel execution of functions performing the same task, returning the result from the one that finishes first.
Home-page: https://launchpad.net/txdpce
Author: Fluidinfo Inc.
Author-email: info@fluidinfo.com
License: UNKNOWN
Download-URL: https://code.launchpad.net/txdpce
Keywords: twisted parallel command execution
Platform: UNKNOWN
Classifier: Programming Language :: Python
Classifier: Framework :: Twisted
Classifier: Development Status :: 4 - Beta
Classifier: Intended Audience :: Developers
Classifier: License :: OSI Approved :: Apache Software License
Classifier: Operating System :: OS Independent
Classifier: Topic :: Software Development :: Libraries :: Python Modules
Provides: txdpce
